pypigeonhole_build/__init__.py
pypigeonhole_build/app_setup.py
pypigeonhole_build/app_version_control.py
pypigeonhole_build/conda_translator.py
pypigeonhole_build/dep_manager.py
pypigeonhole_build/dependency.py
pypigeonhole_build/pip_translator.py
pypigeonhole_build-0.5.0.dist-info/LICENSE.md
pypigeonhole_build-0.5.0.dist-info/METADATA
pypigeonhole_build-0.5.0.dist-info/WHEEL
pypigeonhole_build-0.5.0.dist-info/top_level.txt
pypigeonhole_build-0.5.0.dist-info/RECORD
