Metadata-Version: 2.1
Name: pypigeonhole-build
Version: 0.5.0
Summary: Python build & packaging tool
Home-page: https://github.com/psilons/pypigeonhole-build
Author: psilons
Author-email: psilons.quanta@gmail.com
License: MIT
Platform: UNKNOWN
Requires-Python: >=3.6
License-File: LICENSE.md
